{
  "title": "Developer Tools Tech Radar",
  "quadrants": [
    {
      "id": "1",
      "name": "Languages and Frameworks"
    },
    {
      "id": "2",
      "name": "Development Tools"
    },
    {
      "id": "3",
      "name": "Testing"
    },
    {
      "id": "4",
      "name": "CI/CD"
    }
  ],
  "rings": [
    {
      "id": "adopt",
      "name": "ADOPT",
      "color": "#93c47d"
    },
    {
      "id": "trial",
      "name": "TRIAL",
      "color": "#93d2c2"
    },
    {
      "id": "assess",
      "name": "ASSESS",
      "color": "#fbdb84"
    },
    {
      "id": "hold",
      "name": "HOLD",
      "color": "#efafa9"
    }
  ],
  "entries": [
    {
      "id": "typescript",
      "title": "TypeScript",
      "description": "TypeScript is a strongly typed programming language that builds on JavaScript.",
      "key": "typescript",
      "url": "https://www.typescriptlang.org/",
      "quadrant": "1",
      "timeline": [
        {
          "moved": 1,
          "ringId": "adopt",
          "date": "2023-01-10",
          "description": "Widely adopted in various projects."
        },
        {
          "moved": 0,
          "ringId": "trial",
          "date": "2022-05-15",
          "description": "Undergoing evaluation in various teams."
        }
      ]
    },
    {
      "id": "react",
      "title": "React",
      "description": "A JavaScript library for building user interfaces.",
      "key": "react",
      "url": "https://reactjs.org/",
      "quadrant": "1",
      "timeline": [
        {
          "moved": 1,
          "ringId": "adopt",
          "date": "2023-02-20",
          "description": "Widely adopted for building user interfaces."
        },
        {
          "moved": 0,
          "ringId": "trial",
          "date": "2022-08-01",
          "description": "Under evaluation for front-end development."
        }
      ]
    },
    {
      "id": "vue",
      "title": "Vue.js",
      "description": "A progressive framework for building user interfaces.",
      "key": "vue",
      "url": "https://vuejs.org/",
      "quadrant": "1",
      "timeline": [
        {
          "moved": 1,
          "ringId": "trial",
          "date": "2023-03-15",
          "description": "Under trial for progressive web app development."
        },
        {
          "moved": 0,
          "ringId": "assess",
          "date": "2022-10-10",
          "description": "Being assessed for adoption in new projects."
        }
      ]
    },
    {
      "id": "angular",
      "title": "Angular",
      "description": "A platform for building mobile and desktop web applications.",
      "key": "angular",
      "url": "https://angular.io/",
      "quadrant": "1",
      "timeline": [
        {
          "moved": 1,
          "ringId": "assess",
          "date": "2023-04-05",
          "description": "Being assessed for large-scale applications."
        },
        {
          "moved": 0,
          "ringId": "hold",
          "date": "2022-11-20",
          "description": "On hold for new projects in favor of React and Vue."
        }
      ]
    },
    {
      "id": "vscode",
      "title": "Visual Studio Code",
      "description": "A source-code editor made by Microsoft for Windows, Linux, and macOS.",
      "key": "vscode",
      "url": "https://code.visualstudio.com/",
      "quadrant": "2",
      "timeline": [
        {
          "moved": 1,
          "ringId": "adopt",
          "date": "2023-03-05",
          "description": "Adopted as the primary code editor."
        },
        {
          "moved": 0,
          "ringId": "trial",
          "date": "2022-07-20",
          "description": "Under trial for various development projects."
        }
      ]
    },
    {
      "id": "git",
      "title": "Git",
      "description": "A distributed version-control system for tracking changes in source code during software development.",
      "key": "git",
      "url": "https://git-scm.com/",
      "quadrant": "2",
      "timeline": [
        {
          "moved": 1,
          "ringId": "adopt",
          "date": "2023-04-15",
          "description": "Standard version-control system adopted."
        },
        {
          "moved": 0,
          "ringId": "trial",
          "date": "2022-10-10",
          "description": "Trial phase for version control."
        }
      ]
    },
    {
      "id": "docker",
      "title": "Docker",
      "description": "A set of platform-as-a-service products that use OS-level virtualization to deliver software in packages called containers.",
      "key": "docker",
      "url": "https://www.docker.com/",
      "quadrant": "2",
      "timeline": [
        {
          "moved": 1,
          "ringId": "adopt",
          "date": "2023-06-20",
          "description": "Adopted for container-based development."
        },
        {
          "moved": 0,
          "ringId": "trial",
          "date": "2022-12-05",
          "description": "Trial phase for containerization."
        }
      ]
    },
    {
      "id": "jest",
      "title": "Jest",
      "description": "A delightful JavaScript Testing Framework with a focus on simplicity.",
      "key": "jest",
      "url": "https://jestjs.io/",
      "quadrant": "3",
      "timeline": [
        {
          "moved": 1,
          "ringId": "adopt",
          "date": "2023-05-10",
          "description": "Adopted for unit and integration testing."
        },
        {
          "moved": 0,
          "ringId": "trial",
          "date": "2022-11-05",
          "description": "Under trial for JavaScript testing."
        }
      ]
    },
    {
      "id": "mocha",
      "title": "Mocha",
      "description": "A feature-rich JavaScript test framework running on Node.js and in the browser.",
      "key": "mocha",
      "url": "https://mochajs.org/",
      "quadrant": "3",
      "timeline": [
        {
          "moved": 1,
          "ringId": "trial",
          "date": "2023-06-15",
          "description": "Trial phase for back-end testing."
        },
        {
          "moved": 0,
          "ringId": "assess",
          "date": "2023-01-10",
          "description": "Being assessed for suitability in various projects."
        }
      ]
    },
    {
      "id": "cypress",
      "title": "Cypress",
      "description": "A JavaScript end-to-end testing framework.",
      "key": "cypress",
      "url": "https://www.cypress.io/",
      "quadrant": "3",
      "timeline": [
        {
          "moved": 1,
          "ringId": "adopt",
          "date": "2023-06-08",
          "description": "Adopted for end-to-end testing."
        },
        {
          "moved": 0,
          "ringId": "trial",
          "date": "2023-01-10",
          "description": "Trial phase for automated testing."
        }
      ]
    },
    {
      "id": "selenium",
      "title": "Selenium",
      "description": "A portable framework for testing web applications.",
      "key": "selenium",
      "url": "https://www.selenium.dev/",
      "quadrant": "3",
      "timeline": [
        {
          "moved": 1,
          "ringId": "assess",
          "date": "2023-07-12",
          "description": "Being assessed for cross-browser testing."
        },
        {
          "moved": 0,
          "ringId": "hold",
          "date": "2023-02-18",
          "description": "On hold due to alternative tools like Cypress."
        }
      ]
    },
    {
      "id": "jenkins",
      "title": "Jenkins",
      "description": "An open-source automation server written in Java.",
      "key": "jenkins",
      "url": "https://www.jenkins.io/",
      "quadrant": "4",
      "timeline": [
        {
          "moved": 1,
          "ringId": "adopt",
          "date": "2023-07-20",
          "description": "Adopted for continuous integration and delivery."
        },
        {
          "moved": 0,
          "ringId": "trial",
          "date": "2023-02-15",
          "description": "Under trial for CI/CD pipelines."
        }
      ]
    },
    {
      "id": "github-actions",
      "title": "GitHub Actions",
      "description": "Automate, customize, and execute software development workflows right in your repository with GitHub Actions.",
      "key": "github-actions",
      "url": "https://github.com/features/actions",
      "quadrant": "4",
      "timeline": [
        {
          "moved": 1,
          "ringId": "adopt",
          "date": "2023-08-18",
          "description": "Adopted for CI/CD workflows."
        },
        {
          "moved": 0,
          "ringId": "trial",
          "date": "2023-03-12",
          "description": "Trial phase for GitHub-based CI/CD."
        }
      ]
    },
    {
      "id": "circleci",
      "title": "CircleCI",
      "description": "A continuous integration and continuous delivery platform for DevOps teams.",
      "key": "circleci",
      "url": "https://circleci.com/",
      "quadrant": "4",
      "timeline": [
        {
          "moved": 1,
          "ringId": "trial",
          "date": "2023-09-05",
          "description": "Under trial for continuous delivery pipelines."
        },
        {
          "moved": 0,
          "ringId": "assess",
          "date": "2023-04-01",
          "description": "Being assessed for integration into existing workflows."
        }
      ]
    },
    {
      "id": "travisci",
      "title": "Travis CI",
      "description": "A hosted continuous integration service used to build and test software projects hosted on GitHub.",
      "key": "travisci",
      "url": "https://travis-ci.org/",
      "quadrant": "4",
      "timeline": [
        {
          "moved": 1,
          "ringId": "assess",
          "date": "2023-09-25",
          "description": "Being assessed for suitability in new projects."
        },
        {
          "moved": 0,
          "ringId": "hold",
          "date": "2023-06-15",
          "description": "On hold due to preference for Jenkins and GitHub Actions."
        }
      ]
    }
  ]
}
